electronsandstuff/__init__.py
electronsandstuff/file_interfaces.py
electronsandstuff/plotting.py
electronsandstuff/icool/__init__.py
electronsandstuff/icool/base.py
electronsandstuff/icool/exceptions.py
electronsandstuff/icool/fields.py
electronsandstuff/icool/geometry.py
electronsandstuff/icool/main.py
electronsandstuff/icool/plotting.py
electronsandstuff/icool/region_commands.py
electronsandstuff/icool/substitution.py
electronsandstuff/icool/utils.py
electronsandstuff/paretobench/__init__.py
electronsandstuff/paretobench/pymoo.py
electronsandstuff/paretobench/xopt.py
electronsandstuff/pmd_beamphysics/beam_diff.py
electronsandstuff/xopt/__init__.py
electronsandstuff/xopt/cnsga_to_nsga2.py
electronsandstuff/xopt/deduplicated.py
electronsandstuff-0.0.9.dist-info/licenses/LICENSE.txt
electronsandstuff-0.0.9.dist-info/METADATA
electronsandstuff-0.0.9.dist-info/WHEEL
electronsandstuff-0.0.9.dist-info/top_level.txt
electronsandstuff-0.0.9.dist-info/RECORD
