Metadata-Version: 2.4
Name: electronsandstuff
Version: 0.0.9
Summary: A mono-repo for miscellaneous publicly released code
Author-email: "Christopher M. Pierce" <contact@chris-pierce.com>
License: BSD 3-Clause License
Classifier: Programming Language :: Python :: 3
Classifier: Operating System :: OS Independent
Requires-Python: >=3.10
License-File: LICENSE.txt
Requires-Dist: KDEpy
Requires-Dist: matplotlib
Requires-Dist: numpy
Requires-Dist: openpmd-beamphysics
Requires-Dist: pandas
Requires-Dist: paretobench
Requires-Dist: pillow
Requires-Dist: scipy
Provides-Extra: tests
Requires-Dist: pytest; extra == "tests"
Requires-Dist: xopt; extra == "tests"
Dynamic: license-file
